LICENSE.txt
MANIFEST.in
README.md
setup.cfg
setup.py
src/pymasq/__init__.py
src/pymasq/config.py
src/pymasq.egg-info/PKG-INFO
src/pymasq.egg-info/SOURCES.txt
src/pymasq.egg-info/dependency_links.txt
src/pymasq.egg-info/requires.txt
src/pymasq.egg-info/top_level.txt
src/pymasq/datasets/__init__.py
src/pymasq/datasets/_base.py
src/pymasq/datasets/data_generator.py
src/pymasq/datasets/utils.py
src/pymasq/errors/__init__.py
src/pymasq/kve/__init__.py
src/pymasq/kve/kve.py
src/pymasq/metrics/__init__.py
src/pymasq/metrics/auc_scores.py
src/pymasq/metrics/risk_scores.py
src/pymasq/metrics/suda.py
src/pymasq/metrics/utility_scores.py
src/pymasq/metrics/utils.py
src/pymasq/mitigations/__init__.py
src/pymasq/mitigations/add_noise.py
src/pymasq/mitigations/geom_transform.py
src/pymasq/mitigations/global_recode.py
src/pymasq/mitigations/hashing.py
src/pymasq/mitigations/local_supp.py
src/pymasq/mitigations/microaggregation.py
src/pymasq/mitigations/pram.py
src/pymasq/mitigations/rank_swap.py
src/pymasq/mitigations/rounding.py
src/pymasq/mitigations/shuffle.py
src/pymasq/mitigations/substitute.py
src/pymasq/mitigations/topbot_recoding.py
src/pymasq/mitigations/truncate.py
src/pymasq/mitigations/utils.py
src/pymasq/models/__init__.py
src/pymasq/models/_base.py
src/pymasq/models/models.py
src/pymasq/optimizations/__init__.py
src/pymasq/optimizations/_base.py
src/pymasq/optimizations/optimizations.py
src/pymasq/optimizations/utils.py
src/pymasq/plotting/__init__.py
src/pymasq/plotting/plots.py
src/pymasq/preprocessing/__init__.py
src/pymasq/preprocessing/_base.py
src/pymasq/preprocessing/entity_embedding.py
src/pymasq/preprocessing/preprocess.py
src/pymasq/sa/__init__.py
src/pymasq/sa/sobol.py
src/pymasq/utils/__init__.py
src/pymasq/utils/cache.py
src/pymasq/utils/utils.py