Metadata-Version: 1.2
Name: pymasq
Version: 0.6.5
Summary: Mitigation Assessment and Application for Statistical Disclosure Control
Home-page: UNKNOWN
Author: Cuyler OBrien, Jaime Pena, Evan Young, Brian Levine, Eric Wybenga
Author-email: cuyler.obrien@ll.mit.edu, jdpena@ll.mit.edu, evan.young@ll.mit.edu
License: LICENSE.txt
Platform: UNKNOWN
Requires-Python: >=3.8
